Metadata-Version: 2.1
Name: jira-export
Version: 0.0.3
Summary: Small program for exporting issues from Jira to pdf or html
Home-page: https://github.com/lukaszmach/jira-export
Download-URL: https://github.com/lukaszmach/jira-export/archive/refs/tags/0.0.3.tar.gz
Author: Łukasz Machowski
Author-email: macherek@o2.pl
License-File: LICENSE
